LICENSE.txt
MANIFEST.in
README.md
requirements.txt
setup.cfg
setup.py
python_rabbit_logging/__init__.py
python_rabbit_logging/compat.py
python_rabbit_logging/filters.py
python_rabbit_logging/formatters.py
python_rabbit_logging/handlers.py
python_rabbit_logging/handlers_oneway.py
python_rabbitmq_logging.egg-info/PKG-INFO
python_rabbitmq_logging.egg-info/SOURCES.txt
python_rabbitmq_logging.egg-info/dependency_links.txt
python_rabbitmq_logging.egg-info/requires.txt
python_rabbitmq_logging.egg-info/top_level.txt
python_rabbitmq_logging.egg-info/zip-safe