Metadata-Version: 1.1
Name: python-rabbitmq-logging
Version: 0.0.2
Summary: Send logs to RabbitMQ from Python/Flask
Home-page: https://github.com/aydoganserdar/python-rabbit-logging
Author: Serdar AYDOGAN
Author-email: aydoganserdar@gmail.com
License: MIT
Keywords: logging rabbitmq logs
Platform: UNKNOWN
Classifier: Development Status :: 5 - Production/Stable
Classifier: Intended Audience :: Developers
Classifier: License :: OSI Approved :: MIT License
Classifier: Operating System :: OS Independent
Classifier: Programming Language :: Python
Classifier: Programming Language :: Python :: 2
Classifier: Programming Language :: Python :: 2.7
Classifier: Programming Language :: Python :: 3
Classifier: Programming Language :: Python :: 3.3
Classifier: Programming Language :: Python :: 3.4
Classifier: Programming Language :: Python :: 3.5
Classifier: Programming Language :: Python :: 3.6
